shell.py
avilabsutils_shell-0.0.3.dist-info/METADATA
avilabsutils_shell-0.0.3.dist-info/WHEEL
avilabsutils_shell-0.0.3.dist-info/top_level.txt
avilabsutils_shell-0.0.3.dist-info/RECORD
