Metadata-Version: 2.1
Name: avilabsutils-shell
Version: 0.0.3
Summary: Grab bag of shell utilities.
Home-page: https://github.com/avilay/utils/shell
Author: Avilay Parekh
Author-email: avilay@gmail.com
Classifier: Programming Language :: Python :: 3
Classifier: License :: OSI Approved :: MIT License
Classifier: Operating System :: OS Independent
Requires-Python: >=3.6
